crew/__init__.py
crew/dynamic_agent.py
crew/dynamic_agent_task.py
structsense/__init__.py
structsense/app.py
structsense/cli.py
structsense/default_config_sie/embedding.yaml
structsense/default_config_sie/human_in_loop.yaml
structsense/default_config_sie/ner_agent.yaml
structsense/default_config_sie/ner_task.yaml
structsense/default_config_sie/search_ontology_knowledge.yaml
structsense/default_config_sie_ner.py
structsense/humanloop.py
utils/__init__.py
utils/ontology_knowedge_tool.py
utils/types.py
utils/utils.py
structsense-1.4.1.dist-info/LICENSE.txt
structsense-1.4.1.dist-info/METADATA
structsense-1.4.1.dist-info/WHEEL
structsense-1.4.1.dist-info/entry_points.txt
structsense-1.4.1.dist-info/RECORD
