Metadata-Version: 2.3
Name: structsense
Version: 1.4.1
Summary: structsense is a powerful multi-agent system designed to extract structured information from unstructured data. By orchestrating intelligent agents, it helps you make sense of complex information — hence the name structsense. Whether you're working with scientific texts, documents, or messy data, structsense enables you to transform it into meaningful, structured insights.
License: Apache-2.0
Keywords: python,package,template
Author: tekrajchhetri
Author-email: tekraj@mit.edu
Maintainer: tekrajchhetri
Maintainer-email: tekraj@mit.edu
Requires-Python: >=3.10,<3.13
Classifier: Development Status :: 4 - Beta
Classifier: Programming Language :: Python :: 3.10
Classifier: License :: OSI Approved :: Apache Software License
Classifier: Operating System :: OS Independent
Requires-Dist: click (>=8.1.7,<9.0.0)
Requires-Dist: crewai[tools] (>=0.108.0,<0.109.0)
Requires-Dist: grobidarticleextractor (>=0.7.0,<0.8.0)
Requires-Dist: mlflow (>=2.21.1,<3.0.0)
Requires-Dist: pandas (>=2.2.3,<3.0.0)
Requires-Dist: poetry (>=2.1.1,<3.0.0)
Requires-Dist: python-dotenv (>=1.0.1,<2.0.0)
Requires-Dist: pyyaml (>=6.0.2,<7.0.0)
Requires-Dist: rdflib (>=7.1.3,<8.0.0)
Requires-Dist: rich (>=13.9.4,<14.0.0)
Requires-Dist: weave (>=0.51.39,<0.52.0)
Requires-Dist: weaviate-client (>=4.11.2,<5.0.0)
Project-URL: Documentation, https://docs.brainkb.org/
Project-URL: Homepage, https://github.com/sensein/ner_framework
Project-URL: Repository, https://github.com/sensein/ner_framework
